openapi_to_mcp/converter.py
openapi_to_mcp/filter.py
openapi_to_mcp/integrations/fastapi.py
openapi_to_mcp/parser.py
openapi_to_mcp/resolver.py
openapi_to_mcp-0.1.1.dist-info/LICENSE
openapi_to_mcp-0.1.1.dist-info/METADATA
openapi_to_mcp-0.1.1.dist-info/WHEEL
openapi_to_mcp-0.1.1.dist-info/RECORD
