Metadata-Version: 2.3
Name: openapi-to-mcp
Version: 0.1.1
Summary: A Python library to automatically convert any OpenAPI v2/v3 specification into a Model Context Protocol (MCP) server, with integrations for popular frameworks like FastAPI.
License: MPL-2.0
Keywords: openapi,mcp,fastapi,api,converter,generator
Author: Sriram Krishna
Requires-Python: >=3.8,<4.0
Classifier: License :: OSI Approved
Classifier: Programming Language :: Python :: 3
Classifier: Programming Language :: Python :: 3.8
Classifier: Programming Language :: Python :: 3.9
Classifier: Programming Language :: Python :: 3.10
Classifier: Programming Language :: Python :: 3.11
Classifier: Programming Language :: Python :: 3.12
Classifier: Programming Language :: Python :: 3.13
Requires-Dist: fastapi (>=0.109.2,<0.110.0)
Requires-Dist: jsonpath-ng (>=1.5.3,<2.0.0)
Requires-Dist: jsonpointer (>=2.4,<3.0)
Requires-Dist: pyyaml (>=6.0,<7.0)
Requires-Dist: uvicorn (>=0.27.1,<0.28.0)
Project-URL: Homepage, https://github.com/itssri5/openapi-to-mcp
Project-URL: Repository, https://github.com/itssri5/openapi-to-mcp
